fortic/__init__.py
fortic/fortic.py
fortic/fortinet.py
fortic-0.1.dist-info/METADATA
fortic-0.1.dist-info/WHEEL
fortic-0.1.dist-info/entry_points.txt
fortic-0.1.dist-info/top_level.txt
fortic-0.1.dist-info/RECORD
