Metadata-Version: 2.1
Name: fortic
Version: 0.1
Summary: Fortinet SSLVPN command line interface
Home-page: https://github.com/hacki11/fortic
Author: Juergen Schmid
Author-email: jur.schmid@gmail.com
License: apache-2.0
Keywords: vpn,fortinet,sslvpn,cli
Platform: UNKNOWN
Classifier: Intended Audience :: Developers
Classifier: Topic :: Software Development :: Build Tools
Classifier: License :: OSI Approved :: Apache Software License
Classifier: Programming Language :: Python :: 3
Classifier: Operating System :: Microsoft :: Windows
Requires-Dist: click
Requires-Dist: keepasshttp
